tests/__init__.py
tests/test_base_validator.py
tests/test_error_collection.py
tests/test_iiif_validator.py
tests/validator_testing_tools.py
tripoli/__init__.py
tripoli/exceptions.py
tripoli/mixins.py
tripoli/tripoli.py
tripoli/validator_logging.py
tripoli/resource_validators/__init__.py
tripoli/resource_validators/annotation_validator.py
tripoli/resource_validators/base_validator.py
tripoli/resource_validators/canvas_validator.py
tripoli/resource_validators/image_content_validator.py
tripoli/resource_validators/manifest_validator.py
tripoli/resource_validators/sequence_validator.py
tripoli-2.0.0.dist-info/DESCRIPTION.rst
tripoli-2.0.0.dist-info/METADATA
tripoli-2.0.0.dist-info/RECORD
tripoli-2.0.0.dist-info/WHEEL
tripoli-2.0.0.dist-info/metadata.json
tripoli-2.0.0.dist-info/top_level.txt
