Metadata-Version: 2.0
Name: tripoli
Version: 2.0.0
Summary: IIIF document validation.
Home-page: https://github.com/DDMAL/tripoli
Author: Alex Parmentier, Andrew Hankinson
Author-email: andrew.hankinson@bodleian.ox.ac.uk
License: https://opensource.org/licenses/MIT
Download-URL: https://github.com/DDMAL/tripoli/tarball/master
Keywords: validator,IIIF
Platform: UNKNOWN
Classifier: License :: OSI Approved :: MIT License
Classifier: Development Status :: 5 - Production/Stable
Classifier: Operating System :: OS Independent
Classifier: Topic :: Software Development :: Quality Assurance
Classifier: Topic :: Multimedia :: Graphics :: Presentation
Classifier: Intended Audience :: Developers
Classifier: Environment :: Web Environment
Classifier: Programming Language :: Python
Requires-Python: >=3.5
Requires-Dist: defusedxml
